finalytics-0.8.8.dist-info/METADATA
finalytics-0.8.8.dist-info/WHEEL
finalytics/__init__.py
finalytics/finalytics.cp39-win_amd64.pyd
finalytics-0.8.8.dist-info/RECORD
