Metadata-Version: 2.4
Name: finalytics
Version: 0.8.8
Classifier: Programming Language :: Rust
Classifier: Programming Language :: Python :: Implementation :: CPython
Classifier: Programming Language :: Python :: Implementation :: PyPy
Requires-Dist: polars>=1.1.0
Requires-Dist: pyarrow>=14.0.0
Requires-Dist: plotly>=5.22.0
Requires-Dist: ipython>=7.0.0
Requires-Python: >=3.9
